odoo/addons/purchase_split_wizard_deposit/README.rst
odoo/addons/purchase_split_wizard_deposit/__init__.py
odoo/addons/purchase_split_wizard_deposit/__manifest__.py
odoo/addons/purchase_split_wizard_deposit/i18n/es.po
odoo/addons/purchase_split_wizard_deposit/models/__init__.py
odoo/addons/purchase_split_wizard_deposit/models/purchase_order_line.py
odoo/addons/purchase_split_wizard_deposit/readme/CONTRIBUTORS.md
odoo/addons/purchase_split_wizard_deposit/readme/DESCRIPTION.md
odoo/addons/purchase_split_wizard_deposit/readme/USAGE.md
odoo/addons/purchase_split_wizard_deposit/security/ir.model.access.csv
odoo/addons/purchase_split_wizard_deposit/static/description/icon.png
odoo/addons/purchase_split_wizard_deposit/static/description/index.html
odoo/addons/purchase_split_wizard_deposit/tests/__init__.py
odoo/addons/purchase_split_wizard_deposit/tests/test_purchase_split_wizard_deposit.py
odoo/addons/purchase_split_wizard_deposit/views/purchase_views.xml
odoo/addons/purchase_split_wizard_deposit/wizards/__init__.py
odoo/addons/purchase_split_wizard_deposit/wizards/purchase_split_wizard.py
odoo/addons/purchase_split_wizard_deposit/wizards/purchase_split_wizard_views.xml
odoo_addon_purchase_split_wizard_deposit-16.0.1.0.0.dist-info/METADATA
odoo_addon_purchase_split_wizard_deposit-16.0.1.0.0.dist-info/WHEEL
odoo_addon_purchase_split_wizard_deposit-16.0.1.0.0.dist-info/top_level.txt
odoo_addon_purchase_split_wizard_deposit-16.0.1.0.0.dist-info/RECORD
